{
  "subjects": [
    {
      "id": "math",
      "name": "Mathematics",
      "icon": "math_icon",
      "quizzes": [
        {
          "quizName": "Basic Algebra",
          "description": "Algebraic equations and variables",
          "questions": [
            {
              "type": "single",
              "question": "What is 2 + 2?",
              "options": ["3", "4", "5", "6"],
              "answer": "4",
              "points": 10
            },
            {
              "type": "image_bool",
              "question": "Is this image a triangle?",
              "imagePath": "Images/triangle.png",
              "answer": "true",
              "points": 5
            },
            {
              "type": "multi",
              "question": "Which of these are prime numbers?",
              "options": ["2", "4", "5", "6"],
              "answers": ["2", "5"],
              "points": 15
            }
          ]
        }
      ]
    }
  ]
}
